libray/__init__.py
libray/core.py
libray/ird.py
libray/iso.py
libray/libray
libray/libray.py
libray/sfo.py
libray/data/keys.db
libray-0.0.10.data/scripts/libray
libray-0.0.10.dist-info/COPYING
libray-0.0.10.dist-info/LICENSE.txt
libray-0.0.10.dist-info/METADATA
libray-0.0.10.dist-info/WHEEL
libray-0.0.10.dist-info/top_level.txt
libray-0.0.10.dist-info/RECORD
